[
  {
    "NCONTRATO":133,
    "VIGENCIA":2015,
    "REGIONAL":"CORDOBA",
    "DIRECCIONDEPREVENCION":"PRIMERA INFANCIA",
    "CENTROZONAL":"CZ TIERRALTA",
    "FAMI":24,
    "TRADI":60,
    "SERVICIOS":2
  },
  {
    "NCONTRATO":173,
    "VIGENCIA":2015,
    "REGIONAL":"CORDOBA",
    "DIRECCIONDEPREVENCION":"PRIMERA INFANCIA",
    "CENTROZONAL":"CZ CERETE",
    "FAMI":36,
    "TRADI":159,
    "SERVICIOS":2
  },
   {
    "NCONTRATO":132,
    "VIGENCIA":2015,
    "REGIONAL":"CORDOBA",
    "DIRECCIONDEPREVENCION":"PRIMERA INFANCIA",
    "CENTROZONAL":"CZ MONTELIBANO",
    "FAMI":40,
    "TRADI":124,
    "SERVICIOS":2
  },
  {
    "NCONTRATO":106,
    "VIGENCIA":2015,
    "REGIONAL":"CORDOBA",
    "DIRECCIONDEPREVENCION":"PRIMERA INFANCIA",
    "CENTROZONAL":"CZ BUENAVISTA",
    "FAMI":11,
    "TRADI":21,
    "SERVICIOS":2
  },
  {
    "NCONTRATO":154,
    "VIGENCIA":2015,
    "REGIONAL":"CORDOBA",
    "DIRECCIONDEPREVENCION":"PRIMERA INFANCIA",
    "CENTROZONAL":"CZ LORICA",
    "FAMI":50,
    "TRADI":70,
    "SERVICIOS":2
  },
  {
    "NCONTRATO":174,
    "VIGENCIA":2015,
    "REGIONAL":"CORDOBA",
    "DIRECCIONDEPREVENCION":"PRIMERA INFANCIA",
    "CENTROZONAL":"CZ CERETE",
    "FAMI":60,
    "TRADI":89,
    "SERVICIOS":2
  }
]